torchtrain/__init__.py
torchtrain/callbacks.py
torchtrain/metrics.py
torchtrain/trainer.py
torchtrain/utils.py
torchtrain-0.4.13.dist-info/LICENSE
torchtrain-0.4.13.dist-info/METADATA
torchtrain-0.4.13.dist-info/WHEEL
torchtrain-0.4.13.dist-info/top_level.txt
torchtrain-0.4.13.dist-info/RECORD
